AUTHORS
LICENSE
MANIFEST.in
README.rst
setup.cfg
setup.py
atlssncli/__init__.py
atlssncli/agent.py
atlssncli/agenthandler.py
atlssncli/agile.py
atlssncli/atlssn.py
atlssncli/board.py
atlssncli/boardhandler.py
atlssncli/build.py
atlssncli/buildhandler.py
atlssncli/cached.py
atlssncli/commandgroup.py
atlssncli/commandhandler.py
atlssncli/config.py
atlssncli/docs.py
atlssncli/git.py
atlssncli/gitcontext.py
atlssncli/info.py
atlssncli/infohandler.py
atlssncli/issue.py
atlssncli/issuehandler.py
atlssncli/project.py
atlssncli/projecthandler.py
atlssncli/querybuilder.py
atlssncli/sprint.py
atlssncli/sprinthandler.py
atlssncli/util.py
atlssncli.egg-info/PKG-INFO
atlssncli.egg-info/SOURCES.txt
atlssncli.egg-info/dependency_links.txt
atlssncli.egg-info/entry_points.txt
atlssncli.egg-info/requires.txt
atlssncli.egg-info/top_level.txt
atlssncli/rest/__init__.py
atlssncli/rest/agileclient.py
atlssncli/rest/bambooclient.py
atlssncli/rest/jiraclient.py
tests/__init__.py